krl_model_zoo/__init__.py
krl_model_zoo/__main__.py
krl_model_zoo/env_check.py
krl_model_zoo/py.typed
krl_model_zoo/tier_guard.py
krl_model_zoo/validation.py
krl_model_zoo/audio/__init__.py
krl_model_zoo/core/__init__.py
krl_model_zoo/core/causal_gates.py
krl_model_zoo/core/causal_positional_encoding.py
krl_model_zoo/core/equity_attention.py
krl_model_zoo/multimodal/__init__.py
krl_model_zoo/nlp/__init__.py
krl_model_zoo/time_series/__init__.py
krl_model_zoo/vision/__init__.py
krl_model_zoo-2.0.2.dist-info/licenses/LICENSE
krl_model_zoo-2.0.2.dist-info/licenses/NOTICE
krl_model_zoo-2.0.2.dist-info/METADATA
krl_model_zoo-2.0.2.dist-info/WHEEL
krl_model_zoo-2.0.2.dist-info/top_level.txt
krl_model_zoo-2.0.2.dist-info/RECORD
