Metadata-Version: 2.4
Name: krl-model-zoo
Version: 2.0.2
Summary: Community tier: 20 essential open-source models for vision, NLP, time series, audio, and multimodal tasks. FREE forever.
Author-email: KR-Labs Team <info@krlabs.dev>
Maintainer-email: KR-Labs Team <info@krlabs.dev>
License: Apache-2.0
Project-URL: Homepage, https://github.com/KR-Labs/krl-model-zoo
Project-URL: Documentation, https://krl-model-zoo.readthedocs.io
Project-URL: Repository, https://github.com/KR-Labs/krl-model-zoo
Project-URL: Bug Tracker, https://github.com/KR-Labs/krl-model-zoo/issues
Project-URL: Changelog, https://github.com/KR-Labs/krl-model-zoo/blob/main/CHANGELOG.md
Keywords: deep-learning,machine-learning,computer-vision,nlp,time-series,multimodal,audio,speech-recognition,transformer,model-zoo,pytorch,tensorflow
Classifier: Development Status :: 5 - Production/Stable
Classifier: Intended Audience :: Science/Research
Classifier: Intended Audience :: Developers
Classifier: Intended Audience :: Education
Classifier: License :: OSI Approved :: Apache Software License
Classifier: Operating System :: OS Independent
Classifier: Programming Language :: Python :: 3
Classifier: Programming Language :: Python :: 3.11
Classifier: Programming Language :: Python :: 3.12
Classifier: Programming Language :: Python :: 3.13
Classifier: Topic :: Scientific/Engineering
Classifier: Topic :: Scientific/Engineering :: Artificial Intelligence
Classifier: Topic :: Software Development :: Libraries :: Python Modules
Classifier: Typing :: Typed
Requires-Python: >=3.11
License-File: LICENSE
License-File: NOTICE
Requires-Dist: numpy>=1.26.0
Requires-Dist: torch>=2.0.0
Requires-Dist: torchvision>=0.15.0
Requires-Dist: transformers>=4.30.0
Requires-Dist: pillow>=9.0.0
Requires-Dist: gensim>=4.3.0
Provides-Extra: vision
Requires-Dist: ultralytics>=8.0.0; extra == "vision"
Provides-Extra: audio
Requires-Dist: speechbrain>=0.5.0; extra == "audio"
Provides-Extra: tabular
Requires-Dist: pytorch-tabnet>=4.0; extra == "tabular"
Provides-Extra: dev
Requires-Dist: black>=23.0.0; extra == "dev"
Requires-Dist: isort>=5.12.0; extra == "dev"
Requires-Dist: flake8>=6.0.0; extra == "dev"
Requires-Dist: mypy>=1.0.0; extra == "dev"
Requires-Dist: pre-commit>=3.0.0; extra == "dev"
Requires-Dist: ruff>=0.1.0; extra == "dev"
Provides-Extra: test
Requires-Dist: pytest>=7.2.0; extra == "test"
Requires-Dist: pytest-cov>=4.0.0; extra == "test"
Requires-Dist: pytest-xdist>=3.0.0; extra == "test"
Requires-Dist: pytest-mock>=3.10.0; extra == "test"
Requires-Dist: hypothesis>=6.0.0; extra == "test"
Provides-Extra: docs
Requires-Dist: sphinx>=7.0.0; extra == "docs"
Requires-Dist: sphinx-rtd-theme>=1.3.0; extra == "docs"
Requires-Dist: sphinx-autodoc-typehints>=1.24.0; extra == "docs"
Requires-Dist: sphinx-copybutton>=0.5.2; extra == "docs"
Requires-Dist: myst-parser>=2.0.0; extra == "docs"
Requires-Dist: nbsphinx>=0.9.0; extra == "docs"
Requires-Dist: ipython>=8.0.0; extra == "docs"
Provides-Extra: all
Requires-Dist: krl-model-zoo[audio,dev,docs,tabular,test,vision]; extra == "all"
Dynamic: license-file
